django_model_logging-1.0.0.dist-info/DESCRIPTION.rst
django_model_logging-1.0.0.dist-info/METADATA
django_model_logging-1.0.0.dist-info/metadata.json
django_model_logging-1.0.0.dist-info/RECORD
django_model_logging-1.0.0.dist-info/top_level.txt
django_model_logging-1.0.0.dist-info/WHEEL
model_logging/__init__.py
model_logging/models.py
model_logging/serializers.py
model_logging/views.py
model_logging/migrations/0001_initial.py
model_logging/migrations/0001_squashed_0004_remove_old_field.py
model_logging/migrations/0002_add_new_data_field.py
model_logging/migrations/0003_data_migration.py
model_logging/migrations/0004_remove_old_field.py
model_logging/migrations/__init__.py
model_logging/tests/__init__.py
model_logging/tests/factories.py
model_logging/tests/run.py
model_logging/tests/test_models.py
model_logging/tests/test_serializers.py
model_logging/tests/test_views.py
model_logging/tests/utils.py
