Metadata-Version: 2.0
Name: django-model-logging
Version: 1.0.0
Summary: Generic and secure logging for changes to Django model instances
Home-page: https://github.com/incuna/django-model-logging/
Author: Incuna
Author-email: admin@incuna.com
License: BSD
Platform: UNKNOWN
Classifier: Development Status :: 5 - Production/Stable
Classifier: Framework :: Django
Classifier: Intended Audience :: Developers
Classifier: License :: OSI Approved :: BSD License
Classifier: Natural Language :: English
Classifier: Programming Language :: Python :: 3
Classifier: Programming Language :: Python :: 3.4
Classifier: Programming Language :: Python :: 3 :: Only
Classifier: Topic :: Software Development :: Testing
Requires-Dist: simplejson (<4.0.0,>=3.8.0)
Requires-Dist: djangorestframework (<4.0.0,>=3.2.4)
